pytest_file/__init__.py
pytest_file/__main__.py
pytest_file/py.typed
pytest_file-0.0.0.dist-info/entry_points.txt
pytest_file-0.0.0.dist-info/LICENSE
pytest_file-0.0.0.dist-info/METADATA
pytest_file-0.0.0.dist-info/WHEEL
pytest_file-0.0.0.dist-info/RECORD
