Metadata-Version: 2.1
Name: pytest-file
Version: 0.0.0
Summary: Pytest File
Home-page: https://github.com/56kyle/pytest-file
License: MIT
Author: Kyle Oliver
Author-email: 56kyleoliver@gmail.com
Requires-Python: >=3.9,<4.0
Classifier: Development Status :: 1 - Planning
Classifier: License :: OSI Approved :: MIT License
Classifier: Programming Language :: Python :: 3
Classifier: Programming Language :: Python :: 3.9
Classifier: Programming Language :: Python :: 3.10
Classifier: Programming Language :: Python :: 3.11
Requires-Dist: click (>=8.0.1)
Requires-Dist: twine (>=5.0.0,<6.0.0)
Project-URL: Changelog, https://github.com/56kyle/pytest-file/releases
Project-URL: Documentation, https://pytest-file.readthedocs.io
Project-URL: Repository, https://github.com/56kyle/pytest-file
